AUTHORS
ChangeLog
LICENSE
README.md
requirements.txt
setup.cfg
setup.py
test-requirements.txt
tox.ini
requests_crtauth/__init__.py
requests_crtauth.egg-info/PKG-INFO
requests_crtauth.egg-info/SOURCES.txt
requests_crtauth.egg-info/dependency_links.txt
requests_crtauth.egg-info/not-zip-safe
requests_crtauth.egg-info/requires.txt
requests_crtauth.egg-info/top_level.txt