Metadata-Version: 1.1
Name: requests-crtauth
Version: 0.4
Summary: A crtauth authentication plugin for Python Requests.
Home-page: UNKNOWN
Author: Nic Cope
Author-email: negz@spotify.com
License: UNKNOWN
Platform: UNKNOWN
Classifier: Programming Language :: Python
Classifier: Topic :: Internet :: WWW/HTTP
Classifier: Intended Audience :: System Administrators
